pydantic_settings/__init__.py
pydantic_settings/cache.py
pydantic_settings/database.py
pydantic_settings/models.py
pydantic_settings/py.typed
pydantic_settings/sentry.py
pydantic_settings/settings.py
django_pydantic_settings-0.7.0.dist-info/LICENSE
django_pydantic_settings-0.7.0.dist-info/WHEEL
django_pydantic_settings-0.7.0.dist-info/METADATA
django_pydantic_settings-0.7.0.dist-info/RECORD
