Metadata-Version: 2.1
Name: django-pydantic-settings
Version: 0.7.0
Summary: Manage Django settings with Pydantic.
Home-page: https://github.com/joshourisman/django-pydantic-settings
License: MIT
Author: Josh Ourisman
Author-email: me@josho.io
Requires-Python: >=3.8,<4.0
Classifier: License :: OSI Approved :: MIT License
Classifier: Programming Language :: Python :: 3
Classifier: Programming Language :: Python :: 3.10
Classifier: Programming Language :: Python :: 3.8
Classifier: Programming Language :: Python :: 3.9
Provides-Extra: sentry
Requires-Dist: Django (>=1.11)
Requires-Dist: pydantic[email] (>=1.8,<2.0)
Requires-Dist: sentry-sdk; extra == "sentry"
Requires-Dist: typing-extensions (>=3.7.4,<5.0.0); python_version < "2.8"
Project-URL: Repository, https://github.com/joshourisman/django-pydantic-settings
